simple_pygame/__init__.py
simple_pygame/constants.py
simple_pygame/exceptions.py
simple_pygame/mixer/__init__.py
simple_pygame/mixer/audio.py
simple_pygame/mixer/pyaudioop.py
simple_pygame/terminal/__init__.py
simple_pygame/terminal/pygetch.py
simple_pygame/transform/__init__.py
simple_pygame-0.1.1.dist-info/LICENSE
simple_pygame-0.1.1.dist-info/METADATA
simple_pygame-0.1.1.dist-info/WHEEL
simple_pygame-0.1.1.dist-info/top_level.txt
simple_pygame-0.1.1.dist-info/RECORD
