Metadata-Version: 2.1
Name: simple_pygame
Version: 0.1.1
Summary: A Python library that provides many features using Pygame and other libraries.
Author: YoutuberTom
License: MIT License
Project-URL: Repository, https://github.com/YoutuberTom/Simple_Pygame
Classifier: Development Status :: 3 - Alpha
Classifier: Intended Audience :: Education
Classifier: License :: OSI Approved :: MIT License
Classifier: Programming Language :: Python :: 3
Requires-Python: >=3.5
License-File: LICENSE
